{
      "custom_piece_apiary" : "Apiary",
      "custom_piece_apiary_description" : "A beekeepers best friend.",
      "custom_piece_apiary_ext1" : "Bee Smoker",
      "custom_piece_apiary_ext2" : "Beekeepers Toolbox",
      "custom_piece_apiary_ext3" : "Bottling Table",
      "custom_piece_apiary_ext4" : "Galdr's Blessing",
      "custom_piece_apiary_ext5" : "Surtr's Conduit",
      "custom_item_honeybread": "Honey Bread",
      "custom_item_honeybread_description": "Bread baked using a honey glaze",
      "custom_item_honeycookedmeat": "Pork Tenderloin",
      "custom_item_honeycookedmeat_description": "Boar meat marinated and cooked with honey.",
      "custom_item_honeycookedneck": "Honey Brushed Neck Tail",
      "custom_item_honeycookedneck_description": "Neck meat marinated and cooked with honey.",
      "custom_item_honeycookedlox": "Barbecued Lox",
      "custom_item_honeycookedlox_description": "Lox meat marinated and cooked with honey.",
      "custom_item_honeysausages": "Honey Sweetened Sausages",
      "custom_item_honeysausages_description": "Sausages sweetened with honey",
      "custom_item_honeyserpentmeat": "Teriyaki Serpent",
      "custom_item_honeyserpentmeat_description": "Serpent meat marinated and cooked with honey.",
      "custom_item_honeyteriyakisalmon": "Teriyaki Salmon",
      "custom_item_honeyteriyakisalmon_description": "Fish marinated and cooked with honey.",
      "custom_item_honeyteriyakisalmonwrap": "Teriyaki Salmon Wrap",
      "custom_item_honeyteriyakisalmonwrap_description": "Fish marinated and cooked with honey in a soft tortilla wrap.",
      "custom_item_odinsdelight": "Odin's Delight",
      "custom_item_odinsdelight_description": "A nutritious Jam using all components Valheim has to offer.",      
      "custom_item_honeyneckjerky": "Neck jerky",
      "custom_item_honeyneckjerky_description": "Neck meat dried and cured with honey.",
      "custom_item_honeymushroomsoup": "Mushroom Miso Soup",
      "custom_item_honeymushroomsoup_description": "A hearty soup containing mushrooms from all across Valheim, sweetened with honey.",
      "custom_item_honeycookeddeer": "Venison Loin",
      "custom_item_honeycookeddeer_description": "Deer meat marinated and cooked with honey.",
      "custom_item_honeycookedwolf": "Marinated Wolf Meat",
      "custom_item_honeycookedwolf_description": "Wolf meat marinated and cooked with honey.",
      "custom_item_honeyloxjerky": "Lox jerky",
      "custom_item_honeyloxjerky_description": "Lox meat dried and cured with honey.",
      "custom_item_honeydeerjerky": "Deer jerky",
      "custom_item_honeydeerjerky_description": "Deer meat dried and cured with honey.",
      "custom_item_honeycookedhare": "Honey Roast Hare",
      "custom_item_honeycookedhare_description": "Hare meat marinated and cooked with honey.",
      "custom_item_honeycookedseeker": "Honey Glazed Seeker Meat",
      "custom_item_honeycookedseeker_description": "Seeker meat marinated and cooked with honey.",
      "custom_item_honeymushroomstew": "Dwarven Mushroom Stew",
      "custom_item_honeymushroomstew_description": "A stew imbued with strange powers from Galdr himself.",
      "custom_item_honeyyellowstew": "Fortified Yellow Stew",
      "custom_item_honeyyellowstew_description": "A stew of immense power.",
      "custom_item_honeydessertpie_uncooked": "Uncooked Carrot Cake",
      "custom_item_honeydessertpie_uncooked_description": "Ready for the oven.",
      "custom_item_honeydessertpie": "Carrot Cake",
      "custom_item_honeydessertpie_description": "Tasty cake sweetened with honey and carrots.",
      "custom_item_honeyharepie_uncooked": "Uncooked Hare Pie",
      "custom_item_honeyharepie_uncooked_description": "Ready for the oven.",
      "custom_item_honeyharepie": "Hare Pie",
      "custom_item_honeyharepie_description": "Delicious pie imbued with the power of Galdr.",
      "custom_item_meadbase_speed": "Mead base: Energy",
      "custom_item_meadbase_speed_description": "Needs to be fermented.",
      "custom_item_mead_speed": "Energy mead",
      "custom_item_mead_speed_description": "Powerful brew that boosts the energy of any Viking. Skål!",
      "se_potion_speed_title" : "Loki's Agility",
      "se_potion_speed_tooltip" : "Increases movement speed.",
      "custom_item_meadbase_damage": "Mead base: Aesir",
      "custom_item_meadbase_damage_description": "Needs to be fermented.",
      "custom_item_mead_damage": "Aesir mead",
      "custom_item_mead_damage_description": "Berserker concoction from the Aesir pantheon using the power of Yggdrasil. Skål!",
      "se_potion_damage_title" : "Odin's Wrath",
      "se_potion_damage_tooltip" : "Boosts all damage.",
      "custom_item_honeycomb": "Seared Honeycomb",
      "custom_item_honeycomb_description": "Crunchy Honeycomb straight from the fire.",
      "se_food_honeycomb_title" : "Sugar Rush",
      "se_food_honeycomb_tooltip" : "Ignore your fatigue.",
      "custom_item_honeyyellowstew_lesser": "Lesser Yellow Stew",
      "custom_item_honeyyellowstew_lesser_description": "A warm, yellow stew.",
      "custom_item_honeycookedvolture" : "Braised Volture Breast",
      "custom_item_honeycookedvolture_description" : "Volture breast chopped & braised by the fire.",
      "custom_item_honeycookedasksvin" : "Fried Asksvin Tail",
      "custom_item_honeycookedasksvin_description" : "Asksvin tail fried in honey.",
      "custom_item_surtrsdelight" : "Surtr's Delight",
      "custom_item_surtrsdelight_description" : "May your fire burn bright.",
      "custom_item_volvasbrew" : "Völva's Brew",
      "custom_item_volvasbrew_description" : "A brew recipe passed down from Völvas, legendary practitioners of Galdr.",
      "custom_item_konungromelette" : "Konungr's Omelette",
      "custom_item_konungromelette_description" : "The mightiest of omelettes."
}